comex/__init__.py
comex/__main__.py
comex/cli.py
comex/codeviews/__init__.py
comex/codeviews/AST/AST.py
comex/codeviews/AST/AST_driver.py
comex/codeviews/AST/__init__.py
comex/codeviews/CFG/CFG.py
comex/codeviews/CFG/CFG_csharp.py
comex/codeviews/CFG/CFG_driver.py
comex/codeviews/CFG/CFG_java.py
comex/codeviews/CFG/__init__.py
comex/codeviews/CST/CST_driver.py
comex/codeviews/CST/__init__.py
comex/codeviews/DFG/DFG_driver.py
comex/codeviews/DFG/__init__.py
comex/codeviews/SDFG/SDFG.py
comex/codeviews/SDFG/SDFG_csharp.py
comex/codeviews/SDFG/SDFG_java.py
comex/codeviews/SDFG/__init__.py
comex/codeviews/combined_graph/__init__.py
comex/codeviews/combined_graph/combined_driver.py
comex/tree_parser/__init__.py
comex/tree_parser/cs_parser.py
comex/tree_parser/custom_parser.py
comex/tree_parser/java_parser.py
comex/tree_parser/parser_driver.py
comex/utils/DFG_utils.py
comex/utils/__init__.py
comex/utils/cs_nodes.py
comex/utils/java_nodes.py
comex/utils/postprocessor.py
comex/utils/preprocessor.py
comex/utils/src_parser.py
comex-0.1.5.dist-info/LICENSE
comex-0.1.5.dist-info/METADATA
comex-0.1.5.dist-info/WHEEL
comex-0.1.5.dist-info/entry_points.txt
comex-0.1.5.dist-info/top_level.txt
comex-0.1.5.dist-info/RECORD
