Metadata-Version: 2.1
Name: comex
Version: 0.1.5
Summary: Generate combined multi-code view graphs
Home-page: https://github.com/IBM/tree-sitter-codeviews
License: Apache-2.0
Classifier: License :: OSI Approved :: Apache Software License
Classifier: Operating System :: OS Independent
Classifier: Programming Language :: Python :: 3
Classifier: Programming Language :: Python :: 3 :: Only
Classifier: Programming Language :: Python :: 3.8
Classifier: Programming Language :: Python :: Implementation :: CPython
Requires-Python: >=3.8
License-File: LICENSE
Requires-Dist: networkx (==2.6.3)
Requires-Dist: tree-sitter (==0.20.1)
Requires-Dist: deepdiff (==5.8.1)
Requires-Dist: pydot (==1.4.1)
Requires-Dist: typer (==0.4.1)
Requires-Dist: loguru (==0.6.0)
Provides-Extra: dev
Requires-Dist: pytest ; extra == 'dev'
Requires-Dist: pytest-cov ; extra == 'dev'
Requires-Dist: tqdm ; extra == 'dev'
Requires-Dist: pqdm ; extra == 'dev'
Requires-Dist: loguru ; extra == 'dev'
Requires-Dist: GitPython ; extra == 'dev'
Requires-Dist: pandas ; extra == 'dev'
